tkPDFViewer/__init__.py
tkPDFViewer/tkPDFViewer.py
tkPDFViewer-0.1.dist-info/LICENSE.txt
tkPDFViewer-0.1.dist-info/METADATA
tkPDFViewer-0.1.dist-info/WHEEL
tkPDFViewer-0.1.dist-info/top_level.txt
tkPDFViewer-0.1.dist-info/RECORD
