Metadata-Version: 2.1
Name: tkPDFViewer
Version: 0.1
Summary: The tkPDFViewer is python library, which allows you to embed the PDF file in your tkinter GUI
Home-page: https://github.com/Roshanpaswan/
Author: Roshan Paswan
Author-email: roshanpaswan121121@gmail.com
License: MIT
Download-URL: https://github.com/Roshanpaswan/tkPDFViewer/archive/0.1.zip
Keywords: PdfViewer,tkinter,pdf
Platform: UNKNOWN
Classifier: Development Status :: 3 - Alpha
Classifier: Intended Audience :: Developers
Classifier: Topic :: Software Development :: Build Tools
Classifier: License :: OSI Approved :: MIT License
Classifier: Programming Language :: Python :: 2.7
Classifier: Programming Language :: Python :: 3
Classifier: Programming Language :: Python :: 3.4
Classifier: Programming Language :: Python :: 3.5
Classifier: Programming Language :: Python :: 3.6
